zlib_ng/_version.pyi
zlib_ng/gzip_ng.py
zlib_ng/_version.py
zlib_ng/zlib_ng.cpython-39-x86_64-linux-gnu.so
zlib_ng/gzip_ng_threaded.py
zlib_ng/__init__.py
zlib_ng/py.typed
zlib_ng/zlib_ng.pyi
zlib_ng/zlib-ng/LICENSE.md
zlib_ng/zlib-ng/README.md
zlib_ng-0.5.1.dist-info/LICENSE
zlib_ng-0.5.1.dist-info/METADATA
zlib_ng-0.5.1.dist-info/RECORD
zlib_ng-0.5.1.dist-info/WHEEL
zlib_ng-0.5.1.dist-info/top_level.txt
