Metadata-Version: 2.1
Name: zlib-ng
Version: 0.5.1
Summary: Drop-in replacement for zlib and gzip modules using zlib-ng
Home-page: https://github.com/pycompression/python-zlib-ng
Author: Leiden University Medical Center
Author-email: r.h.p.vorderman@lumc.nl
License: PSF-2.0
Keywords: zlib-ng zlib compression deflate gzip
Classifier: Programming Language :: Python :: 3 :: Only
Classifier: Programming Language :: Python :: 3
Classifier: Programming Language :: Python :: 3.8
Classifier: Programming Language :: Python :: 3.9
Classifier: Programming Language :: Python :: 3.10
Classifier: Programming Language :: Python :: 3.11
Classifier: Programming Language :: Python :: 3.12
Classifier: Programming Language :: Python :: 3.13
Classifier: Programming Language :: Python :: Implementation :: CPython
Classifier: Programming Language :: Python :: Implementation :: PyPy
Classifier: Programming Language :: C
Classifier: Development Status :: 4 - Beta
Classifier: Topic :: System :: Archiving :: Compression
Classifier: License :: OSI Approved :: Python Software Foundation License
Classifier: Operating System :: POSIX :: Linux
Classifier: Operating System :: MacOS
Classifier: Operating System :: Microsoft :: Windows
Requires-Python: >=3.8
License-File: LICENSE
